vavtools/__init__.py
vavtools/vavtools.py
vavtools-0.0.7.dist-info/LICENSE
vavtools-0.0.7.dist-info/METADATA
vavtools-0.0.7.dist-info/WHEEL
vavtools-0.0.7.dist-info/top_level.txt
vavtools-0.0.7.dist-info/RECORD
